{
	"countries": {
		"USA": {
			"banana": "green_bin"
		}
	}
}

////////////////////////////////////////////////////////////////////////////////////////

{
	"country" : {
		"USA": {
			"New-York" : {
				"blue bin" : {
					"contanin":["plastic", "glass", "hangers", "tetrapack", "metal", "bottle", "bottles", "can", "soda can"],
					"color": ["blue", "transparant bag"],
					"opening shape": ["circular", "circular no linear"],
					"dont put there" : ["plastic bags", "cork"],
					"pictures of bin" : "urlToaPicBlue",
					"what happens to it?" : {
						"plastic" : "UrlToVideoPlastic",
						"metal" : "UrlToVideoMetal",
						"glass" : "UrlToVideoGlass"
					},
					"interesting facts" : {
						"fact 1" : "did you know that blah blah blah?",
						"fact 2" : "did you know that blah blah blah blah?"
					}
				},
				"green bin" : {
					"contanin":["paper", "carton"],
					"color": ["green", "transparant bag"],
					"opening shape": ["linear"],
					"dont put there" : ["plastic bags", "cork", "food"],
					"pictures of bin" : "urlToaPicGreen",
					"what happens to it?" : {
						"paper" : "UrlToVideoPlastic",
						"carton" : "UrlToVideoMetal",
					},
					"interesting facts" : {
						"fact 1" : "did you know that blah blah blah?",
						"fact 2" : "did you know that blah blah blah blah?"
					}
				},
				"general bin" : {
				"contanin" : ["banana", "used tissue", "wet paper", "greesy paper", "plastic bags"],
					"color": ["green", "transparant bag"],
					"opening shape": ["linear"],
					"dont put there" : ["plastic bags", "cork", "food"],
					"pictures of bin" : "urlToaPicGreen",
					"what happens to it?" : {
						"trash" : "videoGoingToSeaOrBuried",
					},
					"interesting facts" : {
						"fact 1" : "did you know that plastic bags go here although they are made of plastic?",
						"fact 2" : "did you know oil should be thrown out in a seald bag in the general trash bin?"
					},
				}
			},
			"Boston" : {}
		},
		"Italy": {
			"Milan": {},
			"Torin": {}
		},
		"Israel": {
			"Jerusalem": {}
		},
		"Brazil" : {
			"Sao-Paolo":{},
			"Rio de Jenero" : {}
		}
	}
}



		
			 

